byrne/__init__.py
byrne/constants.py
byrne/datastructures/__init__.py
byrne/datastructures/expression.py
byrne/datastructures/key_definition.py
byrne/datastructures/table_definition.py
byrne/dynamodb.py
byrne/helpers.py
byrne/marshallers/__init__.py
byrne/marshallers/auto_marshaller.py
byrne/marshallers/marshaller.py
byrne/objectmaps/__init__.py
byrne/objectmaps/object_map.py
byrne/paginators/__init__.py
byrne/paginators/paginator.py
byrne/paginators/query_paginator.py
byrne/paginators/scan_paginator.py
byrne/py.typed
byrne/table.py
byrne/table_view.py
byrne-1.0.0.dist-info/LICENSE
byrne-1.0.0.dist-info/METADATA
byrne-1.0.0.dist-info/WHEEL
byrne-1.0.0.dist-info/RECORD
