Metadata-Version: 2.1
Name: byrne
Version: 1.0.0
Summary: A intelligent DynamoDB frontend for Python 3
License: MIT
Author: Jacob Neil Taylor
Author-email: me@jacobtaylor.id.au
Requires-Python: >=3.10,<4.0
Classifier: License :: OSI Approved :: MIT License
Classifier: Programming Language :: Python :: 3
Classifier: Programming Language :: Python :: 3.10
Classifier: Programming Language :: Python :: 3.11
Classifier: Programming Language :: Python :: 3.12
Requires-Dist: amazon-dax-client (>=2.0.3,<3.0.0)
Requires-Dist: boto3 (>=1.34.17,<2.0.0)
